[
  {
    "date": "2024-12-16T00:04:10+00:00",
    "weather": {
      "coord": {
        "lon": 104.0667,
        "lat": 30.6667
      },
      "weather": [
        {
          "id": 800,
          "main": "Clear",
          "description": "clear sky",
          "icon": "01d"
        }
      ],
      "base": "stations",
      "main": {
        "temp": 1.94,
        "feels_like": 1.94,
        "temp_min": 1.94,
        "temp_max": 1.94,
        "pressure": 1028,
        "humidity": 87,
        "sea_level": 1028,
        "grnd_level": 964
      },
      "visibility": 7000,
      "wind": {
        "speed": 1,
        "deg": 0
      },
      "clouds": {
        "all": 1
      },
      "dt": 1734307208,
      "sys": {
        "type": 1,
        "id": 9674,
        "country": "CN",
        "sunrise": 1734306860,
        "sunset": 1734343471
      },
      "timezone": 28800,
      "id": 1815286,
      "name": "Chengdu",
      "cod": 200
    }
  },
  {
    "date": "2024-12-16T12:01:34+00:00",
    "weather": {
      "coord": {
        "lon": 104.0667,
        "lat": 30.6667
      },
      "weather": [
        {
          "id": 800,
          "main": "Clear",
          "description": "clear sky",
          "icon": "01n"
        }
      ],
      "base": "stations",
      "main": {
        "temp": 10.94,
        "feels_like": 9.4,
        "temp_min": 10.94,
        "temp_max": 10.94,
        "pressure": 1023,
        "humidity": 50,
        "sea_level": 1023,
        "grnd_level": 961
      },
      "visibility": 10000,
      "wind": {
        "speed": 2,
        "deg": 60
      },
      "clouds": {
        "all": 0
      },
      "dt": 1734350494,
      "sys": {
        "type": 1,
        "id": 9674,
        "country": "CN",
        "sunrise": 1734306860,
        "sunset": 1734343471
      },
      "timezone": 28800,
      "id": 1815286,
      "name": "Chengdu",
      "cod": 200
    }
  }
]