[
  {
    "date": "2021-12-03T18:15:04+00:00",
    "weather": {
      "coord": {
        "lon": 104.0667,
        "lat": 30.6667
      },
      "weather": [
        {
          "id": 802,
          "main": "Clouds",
          "description": "scattered clouds",
          "icon": "03n"
        }
      ],
      "base": "stations",
      "main": {
        "temp": 10.67,
        "feels_like": 9.44,
        "temp_min": 10.67,
        "temp_max": 10.67,
        "pressure": 1025,
        "humidity": 63,
        "sea_level": 1025,
        "grnd_level": 965
      },
      "visibility": 10000,
      "wind": {
        "speed": 0.46,
        "deg": 28,
        "gust": 0.56
      },
      "clouds": {
        "all": 28
      },
      "dt": 1638555053,
      "sys": {
        "country": "CN",
        "sunrise": 1638575150,
        "sunset": 1638612135
      },
      "timezone": 28800,
      "id": 1815286,
      "name": "Chengdu",
      "cod": 200
    }
  },
  {
    "date": "2021-12-03T21:10:55+00:00",
    "weather": {
      "coord": {
        "lon": 104.0667,
        "lat": 30.6667
      },
      "weather": [
        {
          "id": 804,
          "main": "Clouds",
          "description": "overcast clouds",
          "icon": "04n"
        }
      ],
      "base": "stations",
      "main": {
        "temp": 10.17,
        "feels_like": 8.94,
        "temp_min": 10.17,
        "temp_max": 10.17,
        "pressure": 1024,
        "humidity": 65,
        "sea_level": 1024,
        "grnd_level": 965
      },
      "visibility": 10000,
      "wind": {
        "speed": 0.69,
        "deg": 13,
        "gust": 0.67
      },
      "clouds": {
        "all": 100
      },
      "dt": 1638565855,
      "sys": {
        "country": "CN",
        "sunrise": 1638575150,
        "sunset": 1638612135
      },
      "timezone": 28800,
      "id": 1815286,
      "name": "Chengdu",
      "cod": 200
    }
  },
  {
    "date": "2021-12-04T00:42:47+00:00",
    "weather": {
      "coord": {
        "lon": 104.0667,
        "lat": 30.6667
      },
      "weather": [
        {
          "id": 701,
          "main": "Mist",
          "description": "mist",
          "icon": "50d"
        }
      ],
      "base": "stations",
      "main": {
        "temp": 7.94,
        "feels_like": 7.94,
        "temp_min": 7.94,
        "temp_max": 7.94,
        "pressure": 1026,
        "humidity": 81
      },
      "visibility": 2500,
      "wind": {
        "speed": 1,
        "deg": 220
      },
      "clouds": {
        "all": 100
      },
      "dt": 1638578296,
      "sys": {
        "type": 1,
        "id": 9674,
        "country": "CN",
        "sunrise": 1638575150,
        "sunset": 1638612135
      },
      "timezone": 28800,
      "id": 1815286,
      "name": "Chengdu",
      "cod": 200
    }
  },
  {
    "date": "2021-12-04T03:12:57+00:00",
    "weather": {
      "coord": {
        "lon": 104.0667,
        "lat": 30.6667
      },
      "weather": [
        {
          "id": 804,
          "main": "Clouds",
          "description": "overcast clouds",
          "icon": "04d"
        }
      ],
      "base": "stations",
      "main": {
        "temp": 12.87,
        "feels_like": 11.65,
        "temp_min": 12.87,
        "temp_max": 12.87,
        "pressure": 1026,
        "humidity": 55,
        "sea_level": 1026,
        "grnd_level": 967
      },
      "visibility": 10000,
      "wind": {
        "speed": 0.93,
        "deg": 31,
        "gust": 0.88
      },
      "clouds": {
        "all": 100
      },
      "dt": 1638587466,
      "sys": {
        "country": "CN",
        "sunrise": 1638575150,
        "sunset": 1638612135
      },
      "timezone": 28800,
      "id": 1815286,
      "name": "Chengdu",
      "cod": 200
    }
  },
  {
    "date": "2021-12-04T06:15:07+00:00",
    "weather": {
      "coord": {
        "lon": 104.0667,
        "lat": 30.6667
      },
      "weather": [
        {
          "id": 804,
          "main": "Clouds",
          "description": "overcast clouds",
          "icon": "04d"
        }
      ],
      "base": "stations",
      "main": {
        "temp": 15.26,
        "feels_like": 14.07,
        "temp_min": 15.26,
        "temp_max": 15.26,
        "pressure": 1022,
        "humidity": 47,
        "sea_level": 1022,
        "grnd_level": 964
      },
      "visibility": 10000,
      "wind": {
        "speed": 1.64,
        "deg": 80,
        "gust": 1.27
      },
      "clouds": {
        "all": 100
      },
      "dt": 1638598252,
      "sys": {
        "country": "CN",
        "sunrise": 1638575150,
        "sunset": 1638612135
      },
      "timezone": 28800,
      "id": 1815286,
      "name": "Chengdu",
      "cod": 200
    }
  },
  {
    "date": "2021-12-04T09:12:58+00:00",
    "weather": {
      "coord": {
        "lon": 104.0667,
        "lat": 30.6667
      },
      "weather": [
        {
          "id": 804,
          "main": "Clouds",
          "description": "overcast clouds",
          "icon": "04d"
        }
      ],
      "base": "stations",
      "main": {
        "temp": 15.36,
        "feels_like": 14.2,
        "temp_min": 15.36,
        "temp_max": 15.36,
        "pressure": 1023,
        "humidity": 48,
        "sea_level": 1023,
        "grnd_level": 964
      },
      "visibility": 10000,
      "wind": {
        "speed": 1.69,
        "deg": 80,
        "gust": 1.51
      },
      "clouds": {
        "all": 100
      },
      "dt": 1638609001,
      "sys": {
        "country": "CN",
        "sunrise": 1638575150,
        "sunset": 1638612135
      },
      "timezone": 28800,
      "id": 1815286,
      "name": "Chengdu",
      "cod": 200
    }
  },
  {
    "date": "2021-12-04T12:20:15+00:00",
    "weather": {
      "coord": {
        "lon": 104.0667,
        "lat": 30.6667
      },
      "weather": [
        {
          "id": 721,
          "main": "Haze",
          "description": "haze",
          "icon": "50n"
        }
      ],
      "base": "stations",
      "main": {
        "temp": 13.94,
        "feels_like": 13.01,
        "temp_min": 13.94,
        "temp_max": 13.94,
        "pressure": 1026,
        "humidity": 62
      },
      "visibility": 5000,
      "wind": {
        "speed": 2,
        "deg": 350
      },
      "clouds": {
        "all": 20
      },
      "dt": 1638620342,
      "sys": {
        "type": 1,
        "id": 9674,
        "country": "CN",
        "sunrise": 1638575150,
        "sunset": 1638612135
      },
      "timezone": 28800,
      "id": 1815286,
      "name": "Chengdu",
      "cod": 200
    }
  }
]