[
  {
    "date": "2022-08-01T18:20:03+00:00",
    "weather": {
      "coord": {
        "lon": 104.0667,
        "lat": 30.6667
      },
      "weather": [
        {
          "id": 802,
          "main": "Clouds",
          "description": "scattered clouds",
          "icon": "03n"
        }
      ],
      "base": "stations",
      "main": {
        "temp": 23.94,
        "feels_like": 24.84,
        "temp_min": 23.94,
        "temp_max": 23.94,
        "pressure": 1006,
        "humidity": 94
      },
      "visibility": 7000,
      "wind": {
        "speed": 8,
        "deg": 170
      },
      "clouds": {
        "all": 40
      },
      "dt": 1659377754,
      "sys": {
        "type": 1,
        "id": 9674,
        "country": "CN",
        "sunrise": 1659392508,
        "sunset": 1659441488
      },
      "timezone": 28800,
      "id": 1815286,
      "name": "Chengdu",
      "cod": 200
    }
  },
  {
    "date": "2022-08-01T21:13:23+00:00",
    "weather": {
      "coord": {
        "lon": 104.0667,
        "lat": 30.6667
      },
      "weather": [
        {
          "id": 804,
          "main": "Clouds",
          "description": "overcast clouds",
          "icon": "04n"
        }
      ],
      "base": "stations",
      "main": {
        "temp": 24.92,
        "feels_like": 25.63,
        "temp_min": 24.92,
        "temp_max": 24.92,
        "pressure": 944,
        "humidity": 83
      },
      "visibility": 10000,
      "wind": {
        "speed": 2.92,
        "deg": 136,
        "gust": 6.16
      },
      "clouds": {
        "all": 94
      },
      "dt": 1659388403,
      "sys": {
        "type": 2,
        "id": 2019076,
        "country": "CN",
        "sunrise": 1659392508,
        "sunset": 1659441488
      },
      "timezone": 28800,
      "id": 1815286,
      "name": "Chengdu",
      "cod": 200
    }
  },
  {
    "date": "2022-08-02T01:43:59+00:00",
    "weather": {
      "coord": {
        "lon": 104.0667,
        "lat": 30.6667
      },
      "weather": [
        {
          "id": 803,
          "main": "Clouds",
          "description": "broken clouds",
          "icon": "04d"
        }
      ],
      "base": "stations",
      "main": {
        "temp": 23.94,
        "feels_like": 24.69,
        "temp_min": 23.94,
        "temp_max": 23.94,
        "pressure": 1007,
        "humidity": 88
      },
      "visibility": 10000,
      "wind": {
        "speed": 1,
        "deg": 360
      },
      "clouds": {
        "all": 75
      },
      "dt": 1659404639,
      "sys": {
        "type": 1,
        "id": 9674,
        "country": "CN",
        "sunrise": 1659392508,
        "sunset": 1659441488
      },
      "timezone": 28800,
      "id": 1815286,
      "name": "Chengdu",
      "cod": 200
    }
  },
  {
    "date": "2022-08-02T04:23:23+00:00",
    "weather": {
      "coord": {
        "lon": 104.0667,
        "lat": 30.6667
      },
      "weather": [
        {
          "id": 800,
          "main": "Clear",
          "description": "clear sky",
          "icon": "01d"
        }
      ],
      "base": "stations",
      "main": {
        "temp": 29.94,
        "feels_like": 33.97,
        "temp_min": 29.94,
        "temp_max": 29.94,
        "pressure": 1008,
        "humidity": 66
      },
      "visibility": 10000,
      "wind": {
        "speed": 1,
        "deg": 0
      },
      "clouds": {
        "all": 0
      },
      "dt": 1659414203,
      "sys": {
        "type": 1,
        "id": 9674,
        "country": "CN",
        "sunrise": 1659392508,
        "sunset": 1659441488
      },
      "timezone": 28800,
      "id": 1815286,
      "name": "Chengdu",
      "cod": 200
    }
  }
]