[
  {
    "date": "2021-01-15T18:51:21+00:00",
    "weather": {
      "coord": {
        "lon": 104.0667,
        "lat": 30.6667
      },
      "weather": [
        {
          "id": 701,
          "main": "Mist",
          "description": "mist",
          "icon": "50n"
        }
      ],
      "base": "stations",
      "main": {
        "temp": 6.71,
        "feels_like": 4.86,
        "temp_min": 4,
        "temp_max": 9.44,
        "pressure": 1020,
        "humidity": 100
      },
      "visibility": 4000,
      "wind": {
        "speed": 1.55,
        "deg": 343
      },
      "clouds": {
        "all": 100
      },
      "dt": 1610736397,
      "sys": {
        "type": 1,
        "id": 9674,
        "country": "CN",
        "sunrise": 1610755288,
        "sunset": 1610792698
      },
      "timezone": 28800,
      "id": 1815286,
      "name": "Chengdu",
      "cod": 200
    }
  },
  {
    "date": "2021-01-15T21:27:59+00:00",
    "weather": {
      "coord": {
        "lon": 104.0667,
        "lat": 30.6667
      },
      "weather": [
        {
          "id": 701,
          "main": "Mist",
          "description": "mist",
          "icon": "50n"
        }
      ],
      "base": "stations",
      "main": {
        "temp": 7.05,
        "feels_like": 4.92,
        "temp_min": 5,
        "temp_max": 8.89,
        "pressure": 1020,
        "humidity": 87
      },
      "visibility": 3800,
      "wind": {
        "speed": 1.44,
        "deg": 339
      },
      "clouds": {
        "all": 95
      },
      "dt": 1610746079,
      "sys": {
        "type": 1,
        "id": 9674,
        "country": "CN",
        "sunrise": 1610755288,
        "sunset": 1610792698
      },
      "timezone": 28800,
      "id": 1815286,
      "name": "Chengdu",
      "cod": 200
    }
  },
  {
    "date": "2021-01-16T01:05:34+00:00",
    "weather": {
      "coord": {
        "lon": 104.0667,
        "lat": 30.6667
      },
      "weather": [
        {
          "id": 701,
          "main": "Mist",
          "description": "mist",
          "icon": "50d"
        }
      ],
      "base": "stations",
      "main": {
        "temp": 9.17,
        "feels_like": 7.71,
        "temp_min": 7,
        "temp_max": 10.56,
        "pressure": 1021,
        "humidity": 76
      },
      "visibility": 4500,
      "wind": {
        "speed": 0.53,
        "deg": 28
      },
      "clouds": {
        "all": 40
      },
      "dt": 1610759072,
      "sys": {
        "type": 1,
        "id": 9674,
        "country": "CN",
        "sunrise": 1610755288,
        "sunset": 1610792698
      },
      "timezone": 28800,
      "id": 1815286,
      "name": "Chengdu",
      "cod": 200
    }
  },
  {
    "date": "2021-01-16T03:56:13+00:00",
    "weather": {
      "coord": {
        "lon": 104.0667,
        "lat": 30.6667
      },
      "weather": [
        {
          "id": 701,
          "main": "Mist",
          "description": "mist",
          "icon": "50d"
        }
      ],
      "base": "stations",
      "main": {
        "temp": 11.04,
        "feels_like": 7.07,
        "temp_min": 8,
        "temp_max": 12.78,
        "pressure": 1024,
        "humidity": 71
      },
      "visibility": 3600,
      "wind": {
        "speed": 4.36,
        "deg": 61
      },
      "clouds": {
        "all": 100
      },
      "dt": 1610769182,
      "sys": {
        "type": 1,
        "id": 9674,
        "country": "CN",
        "sunrise": 1610755288,
        "sunset": 1610792698
      },
      "timezone": 28800,
      "id": 1815286,
      "name": "Chengdu",
      "cod": 200
    }
  },
  {
    "date": "2021-01-16T04:17:25+00:00",
    "weather": {
      "coord": {
        "lon": 104.0667,
        "lat": 30.6667
      },
      "weather": [
        {
          "id": 721,
          "main": "Haze",
          "description": "haze",
          "icon": "50d"
        }
      ],
      "base": "stations",
      "main": {
        "temp": 11.31,
        "feels_like": 7.17,
        "temp_min": 9,
        "temp_max": 12.78,
        "pressure": 1023,
        "humidity": 66
      },
      "visibility": 4000,
      "wind": {
        "speed": 4.36,
        "deg": 61
      },
      "clouds": {
        "all": 40
      },
      "dt": 1610770599,
      "sys": {
        "type": 1,
        "id": 9674,
        "country": "CN",
        "sunrise": 1610755288,
        "sunset": 1610792698
      },
      "timezone": 28800,
      "id": 1815286,
      "name": "Chengdu",
      "cod": 200
    }
  },
  {
    "date": "2021-01-16T04:26:05+00:00",
    "weather": {
      "coord": {
        "lon": 104.0667,
        "lat": 30.6667
      },
      "weather": [
        {
          "id": 721,
          "main": "Haze",
          "description": "haze",
          "icon": "50d"
        }
      ],
      "base": "stations",
      "main": {
        "temp": 11.3,
        "feels_like": 7.16,
        "temp_min": 9,
        "temp_max": 12.78,
        "pressure": 1023,
        "humidity": 66
      },
      "visibility": 4000,
      "wind": {
        "speed": 4.36,
        "deg": 61
      },
      "clouds": {
        "all": 40
      },
      "dt": 1610770980,
      "sys": {
        "type": 1,
        "id": 9674,
        "country": "CN",
        "sunrise": 1610755288,
        "sunset": 1610792698
      },
      "timezone": 28800,
      "id": 1815286,
      "name": "Chengdu",
      "cod": 200
    }
  },
  {
    "date": "2021-01-16T04:34:47+00:00",
    "weather": {
      "coord": {
        "lon": 104.0667,
        "lat": 30.6667
      },
      "weather": [
        {
          "id": 721,
          "main": "Haze",
          "description": "haze",
          "icon": "50d"
        }
      ],
      "base": "stations",
      "main": {
        "temp": 11.3,
        "feels_like": 7.16,
        "temp_min": 9,
        "temp_max": 12.78,
        "pressure": 1023,
        "humidity": 66
      },
      "visibility": 4000,
      "wind": {
        "speed": 4.36,
        "deg": 61
      },
      "clouds": {
        "all": 40
      },
      "dt": 1610770980,
      "sys": {
        "type": 1,
        "id": 9674,
        "country": "CN",
        "sunrise": 1610755288,
        "sunset": 1610792698
      },
      "timezone": 28800,
      "id": 1815286,
      "name": "Chengdu",
      "cod": 200
    }
  },
  {
    "date": "2021-01-16T04:38:08+00:00",
    "weather": {
      "coord": {
        "lon": 104.0667,
        "lat": 30.6667
      },
      "weather": [
        {
          "id": 721,
          "main": "Haze",
          "description": "haze",
          "icon": "50d"
        }
      ],
      "base": "stations",
      "main": {
        "temp": 11.52,
        "feels_like": 7.35,
        "temp_min": 9,
        "temp_max": 12.78,
        "pressure": 1023,
        "humidity": 66
      },
      "visibility": 4000,
      "wind": {
        "speed": 4.46,
        "deg": 65
      },
      "clouds": {
        "all": 40
      },
      "dt": 1610771888,
      "sys": {
        "type": 1,
        "id": 9674,
        "country": "CN",
        "sunrise": 1610755288,
        "sunset": 1610792698
      },
      "timezone": 28800,
      "id": 1815286,
      "name": "Chengdu",
      "cod": 200
    }
  },
  {
    "date": "2021-01-16T05:18:26+00:00",
    "weather": {
      "coord": {
        "lon": 104.0667,
        "lat": 30.6667
      },
      "weather": [
        {
          "id": 721,
          "main": "Haze",
          "description": "haze",
          "icon": "50d"
        }
      ],
      "base": "stations",
      "main": {
        "temp": 11.79,
        "feels_like": 9.92,
        "temp_min": 10,
        "temp_max": 12.78,
        "pressure": 1022,
        "humidity": 62
      },
      "visibility": 4000,
      "wind": {
        "speed": 1,
        "deg": 0
      },
      "clouds": {
        "all": 75
      },
      "dt": 1610774199,
      "sys": {
        "type": 1,
        "id": 9674,
        "country": "CN",
        "sunrise": 1610755288,
        "sunset": 1610792698
      },
      "timezone": 28800,
      "id": 1815286,
      "name": "Chengdu",
      "cod": 200
    }
  }
]