[
  {
    "date": "2021-07-27T18:14:09+00:00",
    "weather": {
      "coord": {
        "lon": 104.0667,
        "lat": 30.6667
      },
      "weather": [
        {
          "id": 802,
          "main": "Clouds",
          "description": "scattered clouds",
          "icon": "03n"
        }
      ],
      "base": "stations",
      "main": {
        "temp": 22.71,
        "feels_like": 23.07,
        "temp_min": 22.71,
        "temp_max": 22.71,
        "pressure": 1001,
        "humidity": 78,
        "sea_level": 1001,
        "grnd_level": 945
      },
      "visibility": 10000,
      "wind": {
        "speed": 1.45,
        "deg": 255,
        "gust": 1.55
      },
      "clouds": {
        "all": 45
      },
      "dt": 1627409476,
      "sys": {
        "country": "CN",
        "sunrise": 1627424328,
        "sunset": 1627473685
      },
      "timezone": 28800,
      "id": 1815286,
      "name": "Chengdu",
      "cod": 200
    }
  },
  {
    "date": "2021-07-27T21:11:05+00:00",
    "weather": {
      "coord": {
        "lon": 104.0667,
        "lat": 30.6667
      },
      "weather": [
        {
          "id": 802,
          "main": "Clouds",
          "description": "scattered clouds",
          "icon": "03n"
        }
      ],
      "base": "stations",
      "main": {
        "temp": 22.07,
        "feels_like": 22.5,
        "temp_min": 22.07,
        "temp_max": 22.07,
        "pressure": 1000,
        "humidity": 83,
        "sea_level": 1000,
        "grnd_level": 944
      },
      "visibility": 10000,
      "wind": {
        "speed": 1.16,
        "deg": 306,
        "gust": 1.23
      },
      "clouds": {
        "all": 42
      },
      "dt": 1627420056,
      "sys": {
        "country": "CN",
        "sunrise": 1627424328,
        "sunset": 1627473685
      },
      "timezone": 28800,
      "id": 1815286,
      "name": "Chengdu",
      "cod": 200
    }
  },
  {
    "date": "2021-07-28T00:40:48+00:00",
    "weather": {
      "coord": {
        "lon": 104.0667,
        "lat": 30.6667
      },
      "weather": [
        {
          "id": 800,
          "main": "Clear",
          "description": "clear sky",
          "icon": "01d"
        }
      ],
      "base": "stations",
      "main": {
        "temp": 25.94,
        "feels_like": 26.76,
        "temp_min": 25.94,
        "temp_max": 25.94,
        "pressure": 1003,
        "humidity": 83
      },
      "visibility": 10000,
      "wind": {
        "speed": 2,
        "deg": 230
      },
      "clouds": {
        "all": 0
      },
      "dt": 1627432555,
      "sys": {
        "type": 1,
        "id": 9674,
        "country": "CN",
        "sunrise": 1627424328,
        "sunset": 1627473685
      },
      "timezone": 28800,
      "id": 1815286,
      "name": "Chengdu",
      "cod": 200
    }
  },
  {
    "date": "2021-07-28T03:13:12+00:00",
    "weather": {
      "coord": {
        "lon": 104.0667,
        "lat": 30.6667
      },
      "weather": [
        {
          "id": 800,
          "main": "Clear",
          "description": "clear sky",
          "icon": "01d"
        }
      ],
      "base": "stations",
      "main": {
        "temp": 29.51,
        "feels_like": 31.75,
        "temp_min": 29.51,
        "temp_max": 29.51,
        "pressure": 1001,
        "humidity": 59,
        "sea_level": 1001,
        "grnd_level": 946
      },
      "visibility": 10000,
      "wind": {
        "speed": 0.51,
        "deg": 311,
        "gust": 0.48
      },
      "clouds": {
        "all": 7
      },
      "dt": 1627441824,
      "sys": {
        "country": "CN",
        "sunrise": 1627424328,
        "sunset": 1627473685
      },
      "timezone": 28800,
      "id": 1815286,
      "name": "Chengdu",
      "cod": 200
    }
  },
  {
    "date": "2021-07-28T06:15:20+00:00",
    "weather": {
      "coord": {
        "lon": 104.0667,
        "lat": 30.6667
      },
      "weather": [
        {
          "id": 800,
          "main": "Clear",
          "description": "clear sky",
          "icon": "01d"
        }
      ],
      "base": "stations",
      "main": {
        "temp": 32.65,
        "feels_like": 35.59,
        "temp_min": 32.65,
        "temp_max": 32.65,
        "pressure": 999,
        "humidity": 50,
        "sea_level": 999,
        "grnd_level": 945
      },
      "visibility": 10000,
      "wind": {
        "speed": 1.02,
        "deg": 112,
        "gust": 1.79
      },
      "clouds": {
        "all": 7
      },
      "dt": 1627452920,
      "sys": {
        "country": "CN",
        "sunrise": 1627424328,
        "sunset": 1627473685
      },
      "timezone": 28800,
      "id": 1815286,
      "name": "Chengdu",
      "cod": 200
    }
  },
  {
    "date": "2021-07-28T09:12:49+00:00",
    "weather": {
      "coord": {
        "lon": 104.0667,
        "lat": 30.6667
      },
      "weather": [
        {
          "id": 801,
          "main": "Clouds",
          "description": "few clouds",
          "icon": "02d"
        }
      ],
      "base": "stations",
      "main": {
        "temp": 32.8,
        "feels_like": 35.62,
        "temp_min": 32.8,
        "temp_max": 32.8,
        "pressure": 998,
        "humidity": 49,
        "sea_level": 998,
        "grnd_level": 944
      },
      "visibility": 10000,
      "wind": {
        "speed": 1.16,
        "deg": 77,
        "gust": 1.57
      },
      "clouds": {
        "all": 14
      },
      "dt": 1627463449,
      "sys": {
        "country": "CN",
        "sunrise": 1627424328,
        "sunset": 1627473685
      },
      "timezone": 28800,
      "id": 1815286,
      "name": "Chengdu",
      "cod": 200
    }
  },
  {
    "date": "2021-07-28T12:18:52+00:00",
    "weather": {
      "coord": {
        "lon": 104.0667,
        "lat": 30.6667
      },
      "weather": [
        {
          "id": 801,
          "main": "Clouds",
          "description": "few clouds",
          "icon": "02n"
        }
      ],
      "base": "stations",
      "main": {
        "temp": 32.94,
        "feels_like": 33.69,
        "temp_min": 32.94,
        "temp_max": 32.94,
        "pressure": 1000,
        "humidity": 40
      },
      "visibility": 10000,
      "wind": {
        "speed": 2,
        "deg": 360
      },
      "clouds": {
        "all": 20
      },
      "dt": 1627474676,
      "sys": {
        "type": 1,
        "id": 9674,
        "country": "CN",
        "sunrise": 1627424328,
        "sunset": 1627473685
      },
      "timezone": 28800,
      "id": 1815286,
      "name": "Chengdu",
      "cod": 200
    }
  },
  {
    "date": "2021-07-28T15:13:47+00:00",
    "weather": {
      "coord": {
        "lon": 104.0667,
        "lat": 30.6667
      },
      "weather": [
        {
          "id": 802,
          "main": "Clouds",
          "description": "scattered clouds",
          "icon": "03n"
        }
      ],
      "base": "stations",
      "main": {
        "temp": 25.93,
        "feels_like": 26.48,
        "temp_min": 25.93,
        "temp_max": 25.93,
        "pressure": 1001,
        "humidity": 73,
        "sea_level": 1001,
        "grnd_level": 945
      },
      "visibility": 10000,
      "wind": {
        "speed": 1.46,
        "deg": 245,
        "gust": 1.63
      },
      "clouds": {
        "all": 45
      },
      "dt": 1627485227,
      "sys": {
        "country": "CN",
        "sunrise": 1627424328,
        "sunset": 1627473685
      },
      "timezone": 28800,
      "id": 1815286,
      "name": "Chengdu",
      "cod": 200
    }
  }
]