[
  {
    "date": "2021-11-21T18:14:03+00:00",
    "weather": {
      "coord": {
        "lon": 104.0667,
        "lat": 30.6667
      },
      "weather": [
        {
          "id": 804,
          "main": "Clouds",
          "description": "overcast clouds",
          "icon": "04n"
        }
      ],
      "base": "stations",
      "main": {
        "temp": 10.48,
        "feels_like": 9.15,
        "temp_min": 10.48,
        "temp_max": 10.48,
        "pressure": 967,
        "humidity": 60
      },
      "visibility": 10000,
      "wind": {
        "speed": 0.45,
        "deg": 0,
        "gust": 1.79
      },
      "clouds": {
        "all": 100
      },
      "dt": 1637518324,
      "sys": {
        "type": 2,
        "id": 2019076,
        "country": "CN",
        "sunrise": 1637537757,
        "sunset": 1637575442
      },
      "timezone": 28800,
      "id": 1815286,
      "name": "Chengdu",
      "cod": 200
    }
  },
  {
    "date": "2021-11-21T21:10:45+00:00",
    "weather": {
      "coord": {
        "lon": 104.0667,
        "lat": 30.6667
      },
      "weather": [
        {
          "id": 804,
          "main": "Clouds",
          "description": "overcast clouds",
          "icon": "04n"
        }
      ],
      "base": "stations",
      "main": {
        "temp": 9.92,
        "feels_like": 8.76,
        "temp_min": 9.92,
        "temp_max": 9.92,
        "pressure": 966,
        "humidity": 65
      },
      "visibility": 10000,
      "wind": {
        "speed": 2.45,
        "deg": 212,
        "gust": 4.95
      },
      "clouds": {
        "all": 100
      },
      "dt": 1637528792,
      "sys": {
        "type": 2,
        "id": 2019076,
        "country": "CN",
        "sunrise": 1637537757,
        "sunset": 1637575442
      },
      "timezone": 28800,
      "id": 1815286,
      "name": "Chengdu",
      "cod": 200
    }
  },
  {
    "date": "2021-11-22T00:42:20+00:00",
    "weather": {
      "coord": {
        "lon": 104.0667,
        "lat": 30.6667
      },
      "weather": [
        {
          "id": 800,
          "main": "Clear",
          "description": "clear sky",
          "icon": "01d"
        }
      ],
      "base": "stations",
      "main": {
        "temp": 8.94,
        "feels_like": 7.96,
        "temp_min": 8.94,
        "temp_max": 8.94,
        "pressure": 1029,
        "humidity": 71
      },
      "visibility": 10000,
      "wind": {
        "speed": 2,
        "deg": 180
      },
      "clouds": {
        "all": 0
      },
      "dt": 1637541590,
      "sys": {
        "type": 1,
        "id": 9674,
        "country": "CN",
        "sunrise": 1637537757,
        "sunset": 1637575442
      },
      "timezone": 28800,
      "id": 1815286,
      "name": "Chengdu",
      "cod": 200
    }
  },
  {
    "date": "2021-11-22T03:13:15+00:00",
    "weather": {
      "coord": {
        "lon": 104.0667,
        "lat": 30.6667
      },
      "weather": [
        {
          "id": 804,
          "main": "Clouds",
          "description": "overcast clouds",
          "icon": "04d"
        }
      ],
      "base": "stations",
      "main": {
        "temp": 12.3,
        "feels_like": 10.81,
        "temp_min": 12.3,
        "temp_max": 12.3,
        "pressure": 1029,
        "humidity": 47,
        "sea_level": 1029,
        "grnd_level": 970
      },
      "visibility": 10000,
      "wind": {
        "speed": 2.1,
        "deg": 156,
        "gust": 3.24
      },
      "clouds": {
        "all": 100
      },
      "dt": 1637550614,
      "sys": {
        "country": "CN",
        "sunrise": 1637537757,
        "sunset": 1637575442
      },
      "timezone": 28800,
      "id": 1815286,
      "name": "Chengdu",
      "cod": 200
    }
  }
]