[
  {
    "date": "2022-09-26T00:46:08+00:00",
    "weather": {
      "coord": {
        "lon": 104.0667,
        "lat": 30.6667
      },
      "weather": [
        {
          "id": 803,
          "main": "Clouds",
          "description": "broken clouds",
          "icon": "04d"
        }
      ],
      "base": "stations",
      "main": {
        "temp": 21.62,
        "feels_like": 22.19,
        "temp_min": 19.94,
        "temp_max": 21.64,
        "pressure": 953,
        "humidity": 90
      },
      "visibility": 6000,
      "wind": {
        "speed": 1,
        "deg": 0
      },
      "clouds": {
        "all": 75
      },
      "dt": 1664153037,
      "sys": {
        "type": 2,
        "id": 2019110,
        "country": "CN",
        "sunrise": 1664146438,
        "sunset": 1664189787
      },
      "timezone": 28800,
      "id": 1815286,
      "name": "Chengdu",
      "cod": 200
    }
  },
  {
    "date": "2022-09-26T12:16:31+00:00",
    "weather": {
      "coord": {
        "lon": 104.0667,
        "lat": 30.6667
      },
      "weather": [
        {
          "id": 804,
          "main": "Clouds",
          "description": "overcast clouds",
          "icon": "04n"
        }
      ],
      "base": "stations",
      "main": {
        "temp": 21.08,
        "feels_like": 21.85,
        "temp_min": 21.08,
        "temp_max": 21.08,
        "pressure": 1013,
        "humidity": 100,
        "sea_level": 1013,
        "grnd_level": 956
      },
      "visibility": 10000,
      "wind": {
        "speed": 0.83,
        "deg": 358,
        "gust": 1.05
      },
      "clouds": {
        "all": 100
      },
      "dt": 1664194333,
      "sys": {
        "type": 2,
        "id": 2019110,
        "country": "CN",
        "sunrise": 1664146438,
        "sunset": 1664189787
      },
      "timezone": 28800,
      "id": 1815286,
      "name": "Chengdu",
      "cod": 200
    }
  }
]