[
  {
    "date": "2021-10-15T18:13:59+00:00",
    "weather": {
      "coord": {
        "lon": 104.0667,
        "lat": 30.6667
      },
      "weather": [
        {
          "id": 804,
          "main": "Clouds",
          "description": "overcast clouds",
          "icon": "04n"
        }
      ],
      "base": "stations",
      "main": {
        "temp": 14.27,
        "feels_like": 13.71,
        "temp_min": 14.27,
        "temp_max": 14.27,
        "pressure": 1027,
        "humidity": 75,
        "sea_level": 1027,
        "grnd_level": 968
      },
      "visibility": 10000,
      "wind": {
        "speed": 1.95,
        "deg": 213,
        "gust": 3.19
      },
      "clouds": {
        "all": 100
      },
      "dt": 1634321366,
      "sys": {
        "country": "CN",
        "sunrise": 1634339186,
        "sunset": 1634380314
      },
      "timezone": 28800,
      "id": 1815286,
      "name": "Chengdu",
      "cod": 200
    }
  },
  {
    "date": "2021-10-15T21:10:28+00:00",
    "weather": {
      "coord": {
        "lon": 104.0667,
        "lat": 30.6667
      },
      "weather": [
        {
          "id": 804,
          "main": "Clouds",
          "description": "overcast clouds",
          "icon": "04n"
        }
      ],
      "base": "stations",
      "main": {
        "temp": 16.03,
        "feels_like": 15.73,
        "temp_min": 16.03,
        "temp_max": 16.03,
        "pressure": 965,
        "humidity": 78
      },
      "visibility": 10000,
      "wind": {
        "speed": 1.45,
        "deg": 191,
        "gust": 2.01
      },
      "clouds": {
        "all": 100
      },
      "dt": 1634332038,
      "sys": {
        "type": 2,
        "id": 2019076,
        "country": "CN",
        "sunrise": 1634339186,
        "sunset": 1634380314
      },
      "timezone": 28800,
      "id": 1815286,
      "name": "Chengdu",
      "cod": 200
    }
  },
  {
    "date": "2021-10-16T00:47:19+00:00",
    "weather": {
      "coord": {
        "lon": 104.0667,
        "lat": 30.6667
      },
      "weather": [
        {
          "id": 802,
          "main": "Clouds",
          "description": "scattered clouds",
          "icon": "03d"
        }
      ],
      "base": "stations",
      "main": {
        "temp": 13.94,
        "feels_like": 14,
        "temp_min": 13.94,
        "temp_max": 13.94,
        "pressure": 1030,
        "humidity": 100
      },
      "visibility": 6000,
      "wind": {
        "speed": 1,
        "deg": 220
      },
      "clouds": {
        "all": 40
      },
      "dt": 1634345145,
      "sys": {
        "type": 1,
        "id": 9674,
        "country": "CN",
        "sunrise": 1634339186,
        "sunset": 1634380314
      },
      "timezone": 28800,
      "id": 1815286,
      "name": "Chengdu",
      "cod": 200
    }
  }
]