[
  {
    "date": "2021-12-04T18:14:59+00:00",
    "weather": {
      "coord": {
        "lon": 104.0667,
        "lat": 30.6667
      },
      "weather": [
        {
          "id": 804,
          "main": "Clouds",
          "description": "overcast clouds",
          "icon": "04n"
        }
      ],
      "base": "stations",
      "main": {
        "temp": 13.01,
        "feels_like": 11.93,
        "temp_min": 13.01,
        "temp_max": 13.01,
        "pressure": 1026,
        "humidity": 60,
        "sea_level": 1026,
        "grnd_level": 967
      },
      "visibility": 10000,
      "wind": {
        "speed": 1.16,
        "deg": 322,
        "gust": 1.36
      },
      "clouds": {
        "all": 100
      },
      "dt": 1638641699,
      "sys": {
        "country": "CN",
        "sunrise": 1638661597,
        "sunset": 1638698537
      },
      "timezone": 28800,
      "id": 1815286,
      "name": "Chengdu",
      "cod": 200
    }
  },
  {
    "date": "2021-12-04T21:11:17+00:00",
    "weather": {
      "coord": {
        "lon": 104.0667,
        "lat": 30.6667
      },
      "weather": [
        {
          "id": 803,
          "main": "Clouds",
          "description": "broken clouds",
          "icon": "04n"
        }
      ],
      "base": "stations",
      "main": {
        "temp": 12.19,
        "feels_like": 11.11,
        "temp_min": 12.19,
        "temp_max": 12.19,
        "pressure": 1025,
        "humidity": 63,
        "sea_level": 1025,
        "grnd_level": 966
      },
      "visibility": 10000,
      "wind": {
        "speed": 1.31,
        "deg": 249,
        "gust": 1.52
      },
      "clouds": {
        "all": 63
      },
      "dt": 1638652277,
      "sys": {
        "country": "CN",
        "sunrise": 1638661597,
        "sunset": 1638698537
      },
      "timezone": 28800,
      "id": 1815286,
      "name": "Chengdu",
      "cod": 200
    }
  },
  {
    "date": "2021-12-05T00:47:06+00:00",
    "weather": {
      "coord": {
        "lon": 104.0667,
        "lat": 30.6667
      },
      "weather": [
        {
          "id": 701,
          "main": "Mist",
          "description": "mist",
          "icon": "50d"
        }
      ],
      "base": "stations",
      "main": {
        "temp": 5.94,
        "feels_like": 5.94,
        "temp_min": 5.94,
        "temp_max": 5.94,
        "pressure": 1027,
        "humidity": 87
      },
      "visibility": 2200,
      "wind": {
        "speed": 1,
        "deg": 220
      },
      "clouds": {
        "all": 41
      },
      "dt": 1638665226,
      "sys": {
        "type": 1,
        "id": 9674,
        "country": "CN",
        "sunrise": 1638661597,
        "sunset": 1638698537
      },
      "timezone": 28800,
      "id": 1815286,
      "name": "Chengdu",
      "cod": 200
    }
  }
]